[{                                                                                                                                                                                                                                                                                                              
  "relation": ["delegate_permission/common.handle_all_urls"],                                       
  "target": {                                                                                                                                                                                                                                                                                                   
    "namespace": "android_app",                                                                                                                                                                                                                                                                                 
    "package_name": "rs.aleksa.shoppinggenerator",
    "sha256_cert_fingerprints": ["108db93e178ae23d76611d7764b09e8a1d36bde4"]
  }
}]
